metadata_from_url/__init__.py
metadata_from_url/_extractor.so
metadata_from_url/extractor.py
metadata_from_url-0.0.6.dist-info/METADATA
metadata_from_url-0.0.6.dist-info/WHEEL
metadata_from_url-0.0.6.dist-info/top_level.txt
metadata_from_url-0.0.6.dist-info/RECORD
