Metadata-Version: 2.1
Name: metadata-from-url
Version: 0.0.6
Summary: Extract metadata from url
Home-page: UNKNOWN
Author: hectortav (Ektoras Tavoularis)
Author-email: <tavhector@gmail.com>
License: UNKNOWN
Keywords: python,metadata,extract
Platform: UNKNOWN
Classifier: Intended Audience :: Developers
Classifier: Programming Language :: Python :: 3
Classifier: Operating System :: Unix
